LICENSE.txt
README.rst
setup.py
aiosmpplib/__init__.py
aiosmpplib/__version__.py
aiosmpplib/broker.py
aiosmpplib/codec.py
aiosmpplib/correlator.py
aiosmpplib/esme.py
aiosmpplib/hook.py
aiosmpplib/jsonutils.py
aiosmpplib/log.py
aiosmpplib/protocol.py
aiosmpplib/ratelimiter.py
aiosmpplib/retrytimer.py
aiosmpplib/sequence.py
aiosmpplib/state.py
aiosmpplib/throttle.py
aiosmpplib/utils.py
aiosmpplib.egg-info/PKG-INFO
aiosmpplib.egg-info/SOURCES.txt
aiosmpplib.egg-info/dependency_links.txt
aiosmpplib.egg-info/requires.txt
aiosmpplib.egg-info/top_level.txt
tests/test_codecs.py
tests/test_correlator.py
tests/test_protocol.py