Metadata-Version: 2.2
Name: aiosmpplib
Version: 0.7.1
Summary: Python asyncio SMPP client library.
Home-page: https://github.com/niksabaldun/aiosmpplib
Author: Nikša Baldun
Author-email: niksa.baldun@gmail.com
License: MIT
Keywords: aiosmpplib,smpp,smpp-client,smpp-protocol,smpp-library,esme,smsc
Classifier: Development Status :: 4 - Beta
Classifier: Intended Audience :: Developers
Classifier: Topic :: Software Development :: Build Tools
Classifier: Topic :: Internet :: WWW/HTTP
Classifier: Topic :: Security
Classifier: Topic :: System :: Installation/Setup
Classifier: Topic :: System :: Networking
Classifier: Topic :: System :: Systems Administration
Classifier: Topic :: Utilities
Classifier: License :: OSI Approved :: MIT License
Classifier: Programming Language :: Python :: 3.7
License-File: LICENSE.txt
Provides-Extra: test
Requires-Dist: tox; extra == "test"
Requires-Dist: pytest; extra == "test"
Requires-Dist: pytest-asyncio; extra == "test"
Requires-Dist: coverage; extra == "test"
Dynamic: author
Dynamic: author-email
Dynamic: classifier
Dynamic: description
Dynamic: description-content-type
Dynamic: home-page
Dynamic: keywords
Dynamic: license
Dynamic: provides-extra
Dynamic: summary
